pyeasyeda/__init__.py
pyeasyeda/birds_eye_view.py
pyeasyeda/clean_up.py
pyeasyeda/close_up.py
pyeasyeda/summary_suggestions.py
pyeasyeda-0.2.8.dist-info/LICENSE
pyeasyeda-0.2.8.dist-info/WHEEL
pyeasyeda-0.2.8.dist-info/METADATA
pyeasyeda-0.2.8.dist-info/RECORD
