Metadata-Version: 2.1
Name: pyeasyeda
Version: 0.2.8
Summary: Make exploratory data analysis easier! 
License: MIT
Author: Luming Yang
Requires-Python: >=3.9,<4.0
Classifier: License :: OSI Approved :: MIT License
Classifier: Programming Language :: Python :: 3
Classifier: Programming Language :: Python :: 3.10
Classifier: Programming Language :: Python :: 3.9
Requires-Dist: altair (>=4.2.0,<5.0.0)
Requires-Dist: matplotlib (>=3.5.1,<4.0.0)
Requires-Dist: numpy (>=1.22.1,<2.0.0)
Requires-Dist: pandas (>=1.3.5,<2.0.0)
Requires-Dist: seaborn (>=0.11.2,<0.12.0)
